vectors2vrt/__init__.py
vectors2vrt-0.1.dist-info/METADATA
vectors2vrt-0.1.dist-info/WHEEL
vectors2vrt-0.1.dist-info/entry_points.txt
vectors2vrt-0.1.dist-info/top_level.txt
vectors2vrt-0.1.dist-info/RECORD
